earthpie/__init__.py
earthpie/plot.py
earthpie/spatial.py
earthpie-0.1.0.dist-info/METADATA
earthpie-0.1.0.dist-info/WHEEL
earthpie-0.1.0.dist-info/top_level.txt
earthpie-0.1.0.dist-info/RECORD
